MANIFEST.in
README.rst
doc.requirements.txt
herringfile
requirements.txt
setup.cfg
setup.py
Herring.egg-info/PKG-INFO
Herring.egg-info/SOURCES.txt
Herring.egg-info/dependency_links.txt
Herring.egg-info/entry_points.txt
Herring.egg-info/requires.txt
Herring.egg-info/top_level.txt
docs/epydoc.conf
herring/__init__.py
herring/argument_helper.py
herring/hack_sys_path.py
herring/herring_app.py
herring/herring_cli.py
herring/herring_file.py
herring/herring_loader.py
herring/herring_main.py
herring/herring_runner.py
herring/herring_settings.py
herring/parallelize.py
herring/task_with_args.py
herring/support/__init__.py
herring/support/application_settings.py
herring/support/comparable_mixin.py
herring/support/graceful_interrupt_handler.py
herring/support/list_helper.py
herring/support/mkdir_p.py
herring/support/path.py
herring/support/safe_edit.py
herring/support/simple_logger.py
herring/support/terminalsize.py
herring/support/toposort2.py
herring/support/touch.py
herring/support/utils.py
tests/__init__.py
tests/test_herring.py
tests/test_lists.py
tests/test_path.py
tests/test_toposort2.py
tests/test_version.py